cipher/__init__.py
cipher/cipher.py
cipher/credentials.py
cipher/fileio.py
cipher/cli/__init__.py
cipher/cli/ciphercmd.py
cipher/core/__init__.py
cipher/core/derivation.py
cipher/core/pkcs7.py
test/__init__.py
test/test_cipher.py
test/test_code_format.py
test/test_credentials.py
test/test_fileio.py
humu1us_cipher-1.0.1.dist-info/LICENSE
humu1us_cipher-1.0.1.dist-info/METADATA
humu1us_cipher-1.0.1.dist-info/WHEEL
humu1us_cipher-1.0.1.dist-info/entry_points.txt
humu1us_cipher-1.0.1.dist-info/top_level.txt
humu1us_cipher-1.0.1.dist-info/RECORD
