Metadata-Version: 2.1
Name: humu1us-cipher
Version: 1.0.1
Summary: Encryption/decryption library
Home-page: https://github.com/humu1us/cipher
Author: Felipe Ortiz, Pablo Ahumada
Author-email: fortizc@gmail.com, pablo.ahumadadiaz@gmail.com
License: MIT
Keywords: AES encryption decryption
Classifier: Development Status :: 5 - Production/Stable
Classifier: Intended Audience :: Developers
Classifier: Topic :: Software Development
Classifier: Topic :: System
Classifier: Topic :: Software Development :: Libraries :: Python Modules
Classifier: Programming Language :: Python :: 3.6
License-File: LICENSE
Requires-Dist: pycryptodome (<4,>=3)
